pwnvasive/__init__.py
pwnvasive/cli.py
pwnvasive/collections.py
pwnvasive/events.py
pwnvasive/exceptions.py
pwnvasive/handlers.py
pwnvasive/main.py
pwnvasive/mappings.py
pwnvasive/operations.py
pwnvasive/os_ops.py
pwnvasive/store.py
pwnvasive-0.1.data/scripts/pwnvasive
pwnvasive-0.1.dist-info/METADATA
pwnvasive-0.1.dist-info/WHEEL
pwnvasive-0.1.dist-info/top_level.txt
pwnvasive-0.1.dist-info/RECORD
